Metadata-Version: 1.0
Name: mscan
Version: 0.0.1
Summary: Looking for a job description on the website monster.com.
Home-page: https://github.com/sm-svyat/monsterscan
Author: UNKNOWN
Author-email: UNKNOWN
License: UNKNOWN
Platform: UNKNOWN
